LICENSE.txt
MANIFEST.in
README.md
setup.cfg
setup.py
casperlabs_client/VERSION
casperlabs_client/__init__.py
casperlabs_client/abi.py
casperlabs_client/annotations_grpc.py
casperlabs_client/annotations_pb2.py
casperlabs_client/annotations_pb2_grpc.py
casperlabs_client/arg_types.py
casperlabs_client/casper_grpc.py
casperlabs_client/casper_pb2.py
casperlabs_client/casper_pb2_grpc.py
casperlabs_client/casperlabs_client.py
casperlabs_client/cli.py
casperlabs_client/common.py
casperlabs_client/consensus_grpc.py
casperlabs_client/consensus_pb2.py
casperlabs_client/consensus_pb2_grpc.py
casperlabs_client/consts.py
casperlabs_client/contract.py
casperlabs_client/control_grpc.py
casperlabs_client/control_pb2.py
casperlabs_client/control_pb2_grpc.py
casperlabs_client/crypto.py
casperlabs_client/decorators.py
casperlabs_client/deploy.py
casperlabs_client/descriptor_grpc.py
casperlabs_client/descriptor_pb2.py
casperlabs_client/descriptor_pb2_grpc.py
casperlabs_client/diagnostics_grpc.py
casperlabs_client/diagnostics_pb2.py
casperlabs_client/diagnostics_pb2_grpc.py
casperlabs_client/empty_grpc.py
casperlabs_client/empty_pb2.py
casperlabs_client/empty_pb2_grpc.py
casperlabs_client/gossiping_grpc.py
casperlabs_client/gossiping_pb2.py
casperlabs_client/gossiping_pb2_grpc.py
casperlabs_client/http_grpc.py
casperlabs_client/http_pb2.py
casperlabs_client/http_pb2_grpc.py
casperlabs_client/info_grpc.py
casperlabs_client/info_pb2.py
casperlabs_client/info_pb2_grpc.py
casperlabs_client/insecure_grpc_service.py
casperlabs_client/io.py
casperlabs_client/ipc_grpc.py
casperlabs_client/ipc_pb2.py
casperlabs_client/ipc_pb2_grpc.py
casperlabs_client/kademlia_grpc.py
casperlabs_client/kademlia_pb2.py
casperlabs_client/kademlia_pb2_grpc.py
casperlabs_client/node_grpc.py
casperlabs_client/node_pb2.py
casperlabs_client/node_pb2_grpc.py
casperlabs_client/query_state.py
casperlabs_client/reformat.py
casperlabs_client/scalapb_grpc.py
casperlabs_client/scalapb_pb2.py
casperlabs_client.egg-info/PKG-INFO
casperlabs_client.egg-info/SOURCES.txt
casperlabs_client.egg-info/dependency_links.txt
casperlabs_client.egg-info/entry_points.txt
casperlabs_client.egg-info/not-zip-safe
casperlabs_client.egg-info/requires.txt
casperlabs_client.egg-info/top_level.txt
