Metadata-Version: 2.1
Name: casperlabs-client
Version: 0.20.1
Summary: Python Client for interacting with a CasperLabs Node
Home-page: https://casperlabs.io/
Author: CasperLabs LLC
Author-email: testing@casperlabs.io
License: CasperLabs Open Source License (COSL)
Project-URL: Source, https://github.com/CasperLabs/CasperLabs/tree/dev/integration-testing/client/CasperLabsClient
Project-URL: Readme, https://github.com/CasperLabs/CasperLabs/blob/dev/integration-testing/client/CasperLabsClient/README.md
Keywords: casperlabs blockchain ethereum smart-contracts
Platform: UNKNOWN
Classifier: Development Status :: 3 - Alpha
Classifier: Programming Language :: Python :: 3.7
Classifier: Programming Language :: Python :: 3 :: Only
Classifier: Operating System :: OS Independent
Classifier: Intended Audience :: Developers
